LICENSE
MANIFEST.in
README.md
setup.py
text2id/__init__.py
text2id/cleaners.py
text2id/cmudict.py
text2id/numbers_normalization.py
text2id/symbols.py
text2id/text2id.py
text2id/u2a.py
text2id/used_types.py
text2id.egg-info/PKG-INFO
text2id.egg-info/SOURCES.txt
text2id.egg-info/dependency_links.txt
text2id.egg-info/not-zip-safe
text2id.egg-info/requires.txt
text2id.egg-info/top_level.txt
text2id/data/cmudict