Metadata-Version: 2.1
Name: text2id
Version: 0.0.1
Summary: Text converter for text to speech tasks.
Home-page: https://github.com/andreyanuf/text2id
Author: Andrey Anufriev
Author-email: a.a.egorovich@gmail.com
License: MIT
Platform: UNKNOWN
Classifier: Programming Language :: Python :: 3
License-File: LICENSE
